README.md
setup.cfg
setup.py
topsis_101903576/__init__.py
topsis_101903576/topsis_101903576.py
topsis_101903576.egg-info/PKG-INFO
topsis_101903576.egg-info/SOURCES.txt
topsis_101903576.egg-info/dependency_links.txt
topsis_101903576.egg-info/entry_points.txt
topsis_101903576.egg-info/top_level.txt