Metadata-Version: 2.1
Name: topsis-101903576
Version: 4.1.0
Summary: Python package to implement TOPSIS
Home-page: https://github.com/ABHISHEK-WD-13/topsis-101903576
Author: Abhishek
Author-email: abhi013lamba@gmail.com
License: MIT
Platform: UNKNOWN
Classifier: License :: OSI Approved :: MIT License
Classifier: Programming Language :: Python :: 3
Classifier: Programming Language :: Python :: 3.7
